[
  {
    "Adjustment Note No": "101",
    "Customer": "Aiman N (deleted)",
    "Adjustment Note Date": 45879,
    "Global Tax Calculation": "TaxExcluded",
    "Service Date": "",
    "Product/Service": "Sales",
    "Product/Service Description": "Created by QB Online to adjust balance for deletion",
    "Product/Service Quantity": "1",
    "Product/Service Rate": "3442.36",
    "Product/Service Amount": "3442.36",
    "Product/Service Tax Code": "Out Of Scope",
    "Product/Service Tax Amount": "0.00",
    "Product/Service Class": "",
    "Note to customer": "",
    "Memo on statement": "",
    "SKU": "",
    "Terms": "",
    "Discount Percent": "",
    "Currency Code": "",
    "Exchange rate": "",
    "Location": ""
  },
  {
    "Adjustment Note No": "102",
    "Customer": "Alex H (deleted)",
    "Adjustment Note Date": 45879,
    "Global Tax Calculation": "TaxExcluded",
    "Service Date": "",
    "Product/Service": "Sales",
    "Product/Service Description": "Created by QB Online to adjust balance for deletion",
    "Product/Service Quantity": "1",
    "Product/Service Rate": "767.82",
    "Product/Service Amount": "767.82",
    "Product/Service Tax Code": "Out Of Scope",
    "Product/Service Tax Amount": "0.00",
    "Product/Service Class": "",
    "Note to customer": "",
    "Memo on statement": "",
    "SKU": "",
    "Terms": "",
    "Discount Percent": "",
    "Currency Code": "",
    "Exchange rate": "",
    "Location": ""
  },
  {
    "Adjustment Note No": "7691",
    "Customer": "David Golos (deleted)",
    "Adjustment Note Date": 45565,
    "Global Tax Calculation": "TaxExcluded",
    "Service Date": "",
    "Product/Service": "Bad Debt",
    "Product/Service Description": "",
    "Product/Service Quantity": "1",
    "Product/Service Rate": "306.88",
    "Product/Service Amount": "306.88",
    "Product/Service Tax Code": "Out Of Scope",
    "Product/Service Tax Amount": "0.00",
    "Product/Service Class": "",
    "Note to customer": "",
    "Memo on statement": "",
    "SKU": "",
    "Terms": "",
    "Discount Percent": "",
    "Currency Code": "",
    "Exchange rate": "",
    "Location": ""
  },
  {
    "Adjustment Note No": "7692",
    "Customer": "Rick De Tommaso (deleted)",
    "Adjustment Note Date": 45565,
    "Global Tax Calculation": "TaxExcluded",
    "Service Date": "",
    "Product/Service": "Bad Debt",
    "Product/Service Description": "Unpaid invoice",
    "Product/Service Quantity": "1",
    "Product/Service Rate": "0.00",
    "Product/Service Amount": "0.00",
    "Product/Service Tax Code": "Out Of Scope",
    "Product/Service Tax Amount": "0.00",
    "Product/Service Class": "",
    "Note to customer": "",
    "Memo on statement": "",
    "SKU": "",
    "Terms": "",
    "Discount Percent": "",
    "Currency Code": "",
    "Exchange rate": "",
    "Location": ""
  },
  {
    "Adjustment Note No": "7693",
    "Customer": "Rick De Tommaso (deleted)",
    "Adjustment Note Date": 45565,
    "Global Tax Calculation": "TaxExcluded",
    "Service Date": "",
    "Product/Service": "Bad Debt",
    "Product/Service Description": "",
    "Product/Service Quantity": "1",
    "Product/Service Rate": "281.88",
    "Product/Service Amount": "281.88",
    "Product/Service Tax Code": "Out Of Scope",
    "Product/Service Tax Amount": "0.00",
    "Product/Service Class": "",
    "Note to customer": "",
    "Memo on statement": "",
    "SKU": "",
    "Terms": "",
    "Discount Percent": "",
    "Currency Code": "",
    "Exchange rate": "",
    "Location": ""
  },
  {
    "Adjustment Note No": "7694",
    "Customer": "Rick De Tommaso (deleted)",
    "Adjustment Note Date": 45565,
    "Global Tax Calculation": "TaxExcluded",
    "Service Date": "",
    "Product/Service": "Bad Debt",
    "Product/Service Description": "",
    "Product/Service Quantity": "1",
    "Product/Service Rate": "546.29",
    "Product/Service Amount": "546.29",
    "Product/Service Tax Code": "Out Of Scope",
    "Product/Service Tax Amount": "0.00",
    "Product/Service Class": "",
    "Note to customer": "",
    "Memo on statement": "",
    "SKU": "",
    "Terms": "",
    "Discount Percent": "",
    "Currency Code": "",
    "Exchange rate": "",
    "Location": ""
  },
  {
    "Adjustment Note No": "7695",
    "Customer": "Stewart Watson (deleted)",
    "Adjustment Note Date": 45565,
    "Global Tax Calculation": "TaxExcluded",
    "Service Date": "",
    "Product/Service": "Bad Debt",
    "Product/Service Description": "",
    "Product/Service Quantity": "1",
    "Product/Service Rate": "279.77",
    "Product/Service Amount": "279.77",
    "Product/Service Tax Code": "Out Of Scope",
    "Product/Service Tax Amount": "0.00",
    "Product/Service Class": "",
    "Note to customer": "",
    "Memo on statement": "",
    "SKU": "",
    "Terms": "",
    "Discount Percent": "",
    "Currency Code": "",
    "Exchange rate": "",
    "Location": ""
  },
  {
    "Adjustment Note No": "7696",
    "Customer": "Maree Barron (deleted)",
    "Adjustment Note Date": 45565,
    "Global Tax Calculation": "TaxExcluded",
    "Service Date": "",
    "Product/Service": "Bad Debt",
    "Product/Service Description": "",
    "Product/Service Quantity": "1",
    "Product/Service Rate": "861.50",
    "Product/Service Amount": "861.50",
    "Product/Service Tax Code": "Out Of Scope",
    "Product/Service Tax Amount": "0.00",
    "Product/Service Class": "",
    "Note to customer": "",
    "Memo on statement": "",
    "SKU": "",
    "Terms": "",
    "Discount Percent": "",
    "Currency Code": "",
    "Exchange rate": "",
    "Location": ""
  },
  {
    "Adjustment Note No": "7697",
    "Customer": "Adam Przezdziecki (deleted)",
    "Adjustment Note Date": 45565,
    "Global Tax Calculation": "TaxExcluded",
    "Service Date": "",
    "Product/Service": "Bad Debt",
    "Product/Service Description": "",
    "Product/Service Quantity": "1",
    "Product/Service Rate": "1959.76",
    "Product/Service Amount": "1959.76",
    "Product/Service Tax Code": "Out Of Scope",
    "Product/Service Tax Amount": "0.00",
    "Product/Service Class": "",
    "Note to customer": "",
    "Memo on statement": "",
    "SKU": "",
    "Terms": "",
    "Discount Percent": "",
    "Currency Code": "",
    "Exchange rate": "",
    "Location": ""
  },
  {
    "Adjustment Note No": "7698",
    "Customer": "Carolyn Song (deleted)",
    "Adjustment Note Date": 45565,
    "Global Tax Calculation": "TaxExcluded",
    "Service Date": "",
    "Product/Service": "Bad Debt",
    "Product/Service Description": "",
    "Product/Service Quantity": "1",
    "Product/Service Rate": "936.21",
    "Product/Service Amount": "936.21",
    "Product/Service Tax Code": "Out Of Scope",
    "Product/Service Tax Amount": "0.00",
    "Product/Service Class": "",
    "Note to customer": "",
    "Memo on statement": "",
    "SKU": "",
    "Terms": "",
    "Discount Percent": "",
    "Currency Code": "",
    "Exchange rate": "",
    "Location": ""
  },
  {
    "Adjustment Note No": "7699",
    "Customer": "David Golos (deleted)",
    "Adjustment Note Date": 45565,
    "Global Tax Calculation": "TaxExcluded",
    "Service Date": "",
    "Product/Service": "Bad Debt",
    "Product/Service Description": "",
    "Product/Service Quantity": "1",
    "Product/Service Rate": "45.00",
    "Product/Service Amount": "45.00",
    "Product/Service Tax Code": "Out Of Scope",
    "Product/Service Tax Amount": "0.00",
    "Product/Service Class": "",
    "Note to customer": "",
    "Memo on statement": "",
    "SKU": "",
    "Terms": "",
    "Discount Percent": "",
    "Currency Code": "",
    "Exchange rate": "",
    "Location": ""
  },
  {
    "Adjustment Note No": "7700",
    "Customer": "Mark Kinsman (deleted)",
    "Adjustment Note Date": 45565,
    "Global Tax Calculation": "TaxExcluded",
    "Service Date": "",
    "Product/Service": "Bad Debt",
    "Product/Service Description": "",
    "Product/Service Quantity": "1",
    "Product/Service Rate": "1697.44",
    "Product/Service Amount": "1697.44",
    "Product/Service Tax Code": "Out Of Scope",
    "Product/Service Tax Amount": "0.00",
    "Product/Service Class": "",
    "Note to customer": "",
    "Memo on statement": "",
    "SKU": "",
    "Terms": "",
    "Discount Percent": "",
    "Currency Code": "",
    "Exchange rate": "",
    "Location": ""
  },
  {
    "Adjustment Note No": "7701",
    "Customer": "Maxim Gunner (deleted)",
    "Adjustment Note Date": 45565,
    "Global Tax Calculation": "TaxExcluded",
    "Service Date": "",
    "Product/Service": "Bad Debt",
    "Product/Service Description": "",
    "Product/Service Quantity": "1",
    "Product/Service Rate": "4109.46",
    "Product/Service Amount": "4109.46",
    "Product/Service Tax Code": "Out Of Scope",
    "Product/Service Tax Amount": "0.00",
    "Product/Service Class": "",
    "Note to customer": "",
    "Memo on statement": "",
    "SKU": "",
    "Terms": "",
    "Discount Percent": "",
    "Currency Code": "",
    "Exchange rate": "",
    "Location": ""
  }
]